taiac/__init__.py
taiac/taiac.py
txdtaiac-4.0.2.dist-info/METADATA
txdtaiac-4.0.2.dist-info/WHEEL
txdtaiac-4.0.2.dist-info/top_level.txt
txdtaiac-4.0.2.dist-info/RECORD
